generatrix_py/__init__.py
generatrix_py/generatrix.py
Generatrix-1.0.19.dist-info/METADATA
Generatrix-1.0.19.dist-info/WHEEL
Generatrix-1.0.19.dist-info/entry_points.txt
Generatrix-1.0.19.dist-info/top_level.txt
Generatrix-1.0.19.dist-info/RECORD
