Metadata-Version: 2.1
Name: Generatrix
Version: 1.0.19
Summary: Generates repo contents markdown
Home-page: https://github.com/kodaman2/generatrix_py
Author: Fernando A. Balandran
Author-email: fredz0003@gmail.com
License: MIT
Platform: UNKNOWN
Classifier: Programming Language :: Python :: 3
Classifier: License :: OSI Approved :: MIT License
Classifier: Operating System :: OS Independent
